{
  "name" : "TabTaggedValuesModel",
  "key" : "org.argouml.uml.ui.TabTaggedValuesModel",
  "type" : "class",
  "position" : {
    "startLine" : 53,
    "startColumn" : 8,
    "endLine" : 53,
    "endColumn" : 13
  },
  "modifiers" : [ "PUBLIC" ],
  "fields" : {
    "serialVersionUID" : {
      "name" : "serialVersionUID",
      "key" : "serialVersionUID",
      "type" : "long",
      "position" : {
        "startLine" : 331,
        "startColumn" : 31,
        "endLine" : 331,
        "endColumn" : 47
      },
      "modifiers" : [ "PRIVATE", "STATIC", "FINAL" ],
      "ignore" : false,
      "memberFieldKey" : "org.argouml.uml.ui.TabTaggedValuesModel/memberField/serialVersionUID",
      "classOrInterfaceKey" : "org.argouml.uml.ui.TabTaggedValuesModel"
    },
    "LOG" : {
      "name" : "LOG",
      "key" : "LOG",
      "type" : "org.apache.log4j.Logger",
      "position" : {
        "startLine" : 56,
        "startColumn" : 33,
        "endLine" : 56,
        "endColumn" : 36
      },
      "modifiers" : [ "PRIVATE", "STATIC", "FINAL" ],
      "ignore" : false,
      "memberFieldKey" : "org.argouml.uml.ui.TabTaggedValuesModel/memberField/LOG",
      "classOrInterfaceKey" : "org.argouml.uml.ui.TabTaggedValuesModel"
    },
    "target" : {
      "name" : "target",
      "key" : "target",
      "type" : "java.lang.Object",
      "position" : {
        "startLine" : 62,
        "startColumn" : 20,
        "endLine" : 62,
        "endColumn" : 26
      },
      "modifiers" : [ "PRIVATE" ],
      "ignore" : false,
      "memberFieldKey" : "org.argouml.uml.ui.TabTaggedValuesModel/memberField/target",
      "classOrInterfaceKey" : "org.argouml.uml.ui.TabTaggedValuesModel"
    }
  },
  "methods" : {
    "getRowCount" : {
      "name" : "getRowCount",
      "key" : "org.argouml.uml.ui.TabTaggedValuesModel/method/getRowCount",
      "type" : "int",
      "position" : {
        "startLine" : 146,
        "startColumn" : 16,
        "endLine" : 146,
        "endColumn" : 27
      },
      "modifiers" : [ "PUBLIC" ],
      "overrideAnnotation" : true,
      "returnType" : null,
      "parameters" : [ ],
      "classOrInterfaceKey" : "org.argouml.uml.ui.TabTaggedValuesModel"
    },
    "getFromCollection" : {
      "name" : "getFromCollection",
      "key" : "org.argouml.uml.ui.TabTaggedValuesModel/method/getFromCollection",
      "type" : "java.lang.Object",
      "position" : {
        "startLine" : 285,
        "startColumn" : 19,
        "endLine" : 285,
        "endColumn" : 36
      },
      "modifiers" : [ "STATIC" ],
      "overrideAnnotation" : false,
      "returnType" : null,
      "parameters" : [ {
        "name" : "collection",
        "key" : "collection",
        "type" : "java.util.Collection",
        "position" : {
          "startLine" : 285,
          "startColumn" : 48,
          "endLine" : 285,
          "endColumn" : 58
        },
        "modifiers" : [ ],
        "ignore" : false,
        "methodKey" : "org.argouml.uml.ui.TabTaggedValuesModel/method/getFromCollection"
      }, {
        "name" : "index",
        "key" : "index",
        "type" : "int",
        "position" : {
          "startLine" : 285,
          "startColumn" : 64,
          "endLine" : 285,
          "endColumn" : 69
        },
        "modifiers" : [ ],
        "ignore" : false,
        "methodKey" : "org.argouml.uml.ui.TabTaggedValuesModel/method/getFromCollection"
      } ],
      "classOrInterfaceKey" : "org.argouml.uml.ui.TabTaggedValuesModel"
    },
    "getColumnName" : {
      "name" : "getColumnName",
      "key" : "org.argouml.uml.ui.TabTaggedValuesModel/method/getColumnName",
      "type" : "java.lang.String",
      "position" : {
        "startLine" : 110,
        "startColumn" : 19,
        "endLine" : 110,
        "endColumn" : 32
      },
      "modifiers" : [ "PUBLIC" ],
      "overrideAnnotation" : true,
      "returnType" : null,
      "parameters" : [ {
        "name" : "c",
        "key" : "c",
        "type" : "int",
        "position" : {
          "startLine" : 110,
          "startColumn" : 37,
          "endLine" : 110,
          "endColumn" : 38
        },
        "modifiers" : [ ],
        "ignore" : false,
        "methodKey" : "org.argouml.uml.ui.TabTaggedValuesModel/method/getColumnName"
      } ],
      "classOrInterfaceKey" : "org.argouml.uml.ui.TabTaggedValuesModel"
    },
    "delayedVetoableChange" : {
      "name" : "delayedVetoableChange",
      "key" : "org.argouml.uml.ui.TabTaggedValuesModel/method/delayedVetoableChange",
      "type" : "void",
      "position" : {
        "startLine" : 324,
        "startColumn" : 17,
        "endLine" : 324,
        "endColumn" : 38
      },
      "modifiers" : [ "PUBLIC" ],
      "overrideAnnotation" : false,
      "returnType" : null,
      "parameters" : [ {
        "name" : "pce",
        "key" : "pce",
        "type" : "java.beans.PropertyChangeEvent",
        "position" : {
          "startLine" : 324,
          "startColumn" : 59,
          "endLine" : 324,
          "endColumn" : 62
        },
        "modifiers" : [ ],
        "ignore" : false,
        "methodKey" : "org.argouml.uml.ui.TabTaggedValuesModel/method/delayedVetoableChange"
      } ],
      "classOrInterfaceKey" : "org.argouml.uml.ui.TabTaggedValuesModel"
    },
    "getColumnClass" : {
      "name" : "getColumnClass",
      "key" : "org.argouml.uml.ui.TabTaggedValuesModel/method/getColumnClass",
      "type" : "java.lang.Class",
      "position" : {
        "startLine" : 124,
        "startColumn" : 18,
        "endLine" : 124,
        "endColumn" : 32
      },
      "modifiers" : [ "PUBLIC" ],
      "overrideAnnotation" : true,
      "returnType" : null,
      "parameters" : [ {
        "name" : "c",
        "key" : "c",
        "type" : "int",
        "position" : {
          "startLine" : 124,
          "startColumn" : 37,
          "endLine" : 124,
          "endColumn" : 38
        },
        "modifiers" : [ ],
        "ignore" : false,
        "methodKey" : "org.argouml.uml.ui.TabTaggedValuesModel/method/getColumnClass"
      } ],
      "classOrInterfaceKey" : "org.argouml.uml.ui.TabTaggedValuesModel"
    },
    "getColumnCount" : {
      "name" : "getColumnCount",
      "key" : "org.argouml.uml.ui.TabTaggedValuesModel/method/getColumnCount",
      "type" : "int",
      "position" : {
        "startLine" : 102,
        "startColumn" : 16,
        "endLine" : 102,
        "endColumn" : 30
      },
      "modifiers" : [ "PUBLIC" ],
      "overrideAnnotation" : true,
      "returnType" : null,
      "parameters" : [ ],
      "classOrInterfaceKey" : "org.argouml.uml.ui.TabTaggedValuesModel"
    },
    "addRow" : {
      "name" : "addRow",
      "key" : "org.argouml.uml.ui.TabTaggedValuesModel/method/addRow",
      "type" : "void",
      "position" : {
        "startLine" : 238,
        "startColumn" : 17,
        "endLine" : 238,
        "endColumn" : 23
      },
      "modifiers" : [ "PUBLIC" ],
      "overrideAnnotation" : false,
      "returnType" : null,
      "parameters" : [ {
        "name" : "values",
        "key" : "values",
        "type" : "java.lang.Object[]",
        "position" : {
          "startLine" : 238,
          "startColumn" : 33,
          "endLine" : 238,
          "endColumn" : 39
        },
        "modifiers" : [ ],
        "ignore" : false,
        "methodKey" : "org.argouml.uml.ui.TabTaggedValuesModel/method/addRow"
      } ],
      "classOrInterfaceKey" : "org.argouml.uml.ui.TabTaggedValuesModel"
    },
    "setValueAt" : {
      "name" : "setValueAt",
      "key" : "org.argouml.uml.ui.TabTaggedValuesModel/method/setValueAt",
      "type" : "void",
      "position" : {
        "startLine" : 196,
        "startColumn" : 17,
        "endLine" : 196,
        "endColumn" : 27
      },
      "modifiers" : [ "PUBLIC" ],
      "overrideAnnotation" : true,
      "returnType" : null,
      "parameters" : [ {
        "name" : "aValue",
        "key" : "aValue",
        "type" : "java.lang.Object",
        "position" : {
          "startLine" : 196,
          "startColumn" : 35,
          "endLine" : 196,
          "endColumn" : 41
        },
        "modifiers" : [ ],
        "ignore" : false,
        "methodKey" : "org.argouml.uml.ui.TabTaggedValuesModel/method/setValueAt"
      }, {
        "name" : "rowIndex",
        "key" : "rowIndex",
        "type" : "int",
        "position" : {
          "startLine" : 196,
          "startColumn" : 47,
          "endLine" : 196,
          "endColumn" : 55
        },
        "modifiers" : [ ],
        "ignore" : false,
        "methodKey" : "org.argouml.uml.ui.TabTaggedValuesModel/method/setValueAt"
      }, {
        "name" : "columnIndex",
        "key" : "columnIndex",
        "type" : "int",
        "position" : {
          "startLine" : 196,
          "startColumn" : 61,
          "endLine" : 196,
          "endColumn" : 72
        },
        "modifiers" : [ ],
        "ignore" : false,
        "methodKey" : "org.argouml.uml.ui.TabTaggedValuesModel/method/setValueAt"
      } ],
      "classOrInterfaceKey" : "org.argouml.uml.ui.TabTaggedValuesModel"
    },
    "isCellEditable" : {
      "name" : "isCellEditable",
      "key" : "org.argouml.uml.ui.TabTaggedValuesModel/method/isCellEditable",
      "type" : "boolean",
      "position" : {
        "startLine" : 139,
        "startColumn" : 20,
        "endLine" : 139,
        "endColumn" : 34
      },
      "modifiers" : [ "PUBLIC" ],
      "overrideAnnotation" : true,
      "returnType" : null,
      "parameters" : [ {
        "name" : "row",
        "key" : "row",
        "type" : "int",
        "position" : {
          "startLine" : 139,
          "startColumn" : 39,
          "endLine" : 139,
          "endColumn" : 42
        },
        "modifiers" : [ ],
        "ignore" : false,
        "methodKey" : "org.argouml.uml.ui.TabTaggedValuesModel/method/isCellEditable"
      }, {
        "name" : "col",
        "key" : "col",
        "type" : "int",
        "position" : {
          "startLine" : 139,
          "startColumn" : 48,
          "endLine" : 139,
          "endColumn" : 51
        },
        "modifiers" : [ ],
        "ignore" : false,
        "methodKey" : "org.argouml.uml.ui.TabTaggedValuesModel/method/isCellEditable"
      } ],
      "classOrInterfaceKey" : "org.argouml.uml.ui.TabTaggedValuesModel"
    },
    "getValueAt" : {
      "name" : "getValueAt",
      "key" : "org.argouml.uml.ui.TabTaggedValuesModel/method/getValueAt",
      "type" : "java.lang.Object",
      "position" : {
        "startLine" : 164,
        "startColumn" : 19,
        "endLine" : 164,
        "endColumn" : 29
      },
      "modifiers" : [ "PUBLIC" ],
      "overrideAnnotation" : true,
      "returnType" : null,
      "parameters" : [ {
        "name" : "row",
        "key" : "row",
        "type" : "int",
        "position" : {
          "startLine" : 164,
          "startColumn" : 34,
          "endLine" : 164,
          "endColumn" : 37
        },
        "modifiers" : [ ],
        "ignore" : false,
        "methodKey" : "org.argouml.uml.ui.TabTaggedValuesModel/method/getValueAt"
      }, {
        "name" : "col",
        "key" : "col",
        "type" : "int",
        "position" : {
          "startLine" : 164,
          "startColumn" : 43,
          "endLine" : 164,
          "endColumn" : 46
        },
        "modifiers" : [ ],
        "ignore" : false,
        "methodKey" : "org.argouml.uml.ui.TabTaggedValuesModel/method/getValueAt"
      } ],
      "classOrInterfaceKey" : "org.argouml.uml.ui.TabTaggedValuesModel"
    },
    "setTarget" : {
      "name" : "setTarget",
      "key" : "org.argouml.uml.ui.TabTaggedValuesModel/method/setTarget",
      "type" : "void",
      "position" : {
        "startLine" : 76,
        "startColumn" : 17,
        "endLine" : 76,
        "endColumn" : 26
      },
      "modifiers" : [ "PUBLIC" ],
      "overrideAnnotation" : false,
      "returnType" : null,
      "parameters" : [ {
        "name" : "t",
        "key" : "t",
        "type" : "java.lang.Object",
        "position" : {
          "startLine" : 76,
          "startColumn" : 34,
          "endLine" : 76,
          "endColumn" : 35
        },
        "modifiers" : [ ],
        "ignore" : false,
        "methodKey" : "org.argouml.uml.ui.TabTaggedValuesModel/method/setTarget"
      } ],
      "classOrInterfaceKey" : "org.argouml.uml.ui.TabTaggedValuesModel"
    },
    "removeRow" : {
      "name" : "removeRow",
      "key" : "org.argouml.uml.ui.TabTaggedValuesModel/method/removeRow",
      "type" : "void",
      "position" : {
        "startLine" : 269,
        "startColumn" : 17,
        "endLine" : 269,
        "endColumn" : 26
      },
      "modifiers" : [ "PUBLIC" ],
      "overrideAnnotation" : false,
      "returnType" : null,
      "parameters" : [ {
        "name" : "row",
        "key" : "row",
        "type" : "int",
        "position" : {
          "startLine" : 269,
          "startColumn" : 31,
          "endLine" : 269,
          "endColumn" : 34
        },
        "modifiers" : [ ],
        "ignore" : false,
        "methodKey" : "org.argouml.uml.ui.TabTaggedValuesModel/method/removeRow"
      } ],
      "classOrInterfaceKey" : "org.argouml.uml.ui.TabTaggedValuesModel"
    },
    "propertyChange" : {
      "name" : "propertyChange",
      "key" : "org.argouml.uml.ui.TabTaggedValuesModel/method/propertyChange",
      "type" : "void",
      "position" : {
        "startLine" : 302,
        "startColumn" : 17,
        "endLine" : 302,
        "endColumn" : 31
      },
      "modifiers" : [ "PUBLIC" ],
      "overrideAnnotation" : true,
      "returnType" : null,
      "parameters" : [ {
        "name" : "evt",
        "key" : "evt",
        "type" : "java.beans.PropertyChangeEvent",
        "position" : {
          "startLine" : 302,
          "startColumn" : 52,
          "endLine" : 302,
          "endColumn" : 55
        },
        "modifiers" : [ ],
        "ignore" : false,
        "methodKey" : "org.argouml.uml.ui.TabTaggedValuesModel/method/propertyChange"
      } ],
      "classOrInterfaceKey" : "org.argouml.uml.ui.TabTaggedValuesModel"
    },
    "vetoableChange" : {
      "name" : "vetoableChange",
      "key" : "org.argouml.uml.ui.TabTaggedValuesModel/method/vetoableChange",
      "type" : "void",
      "position" : {
        "startLine" : 316,
        "startColumn" : 17,
        "endLine" : 316,
        "endColumn" : 31
      },
      "modifiers" : [ "PUBLIC" ],
      "overrideAnnotation" : true,
      "returnType" : null,
      "parameters" : [ {
        "name" : "pce",
        "key" : "pce",
        "type" : "java.beans.PropertyChangeEvent",
        "position" : {
          "startLine" : 316,
          "startColumn" : 52,
          "endLine" : 316,
          "endColumn" : 55
        },
        "modifiers" : [ ],
        "ignore" : false,
        "methodKey" : "org.argouml.uml.ui.TabTaggedValuesModel/method/vetoableChange"
      } ],
      "classOrInterfaceKey" : "org.argouml.uml.ui.TabTaggedValuesModel"
    }
  },
  "fileKey" : null,
  "anonymous" : false,
  "auxclass" : false,
  "implements_" : [ "java.beans.VetoableChangeListener", "org.argouml.kernel.DelayedVChangeListener", "java.beans.PropertyChangeListener" ],
  "extends_" : [ "javax.swing.table.AbstractTableModel" ],
  "definedInClassOrInterfaceTypeKey" : null,
  "innerDefinedClasses" : { },
  "innerDefinedInterfaces" : { }
},
