{
  "name" : "SocketOutputStream",
  "key" : "org.apache.commons.net.io.SocketOutputStream",
  "type" : "class",
  "position" : {
    "startLine" : 36,
    "startColumn" : 8,
    "endLine" : 36,
    "endColumn" : 13
  },
  "modifiers" : [ "PUBLIC" ],
  "fields" : {
    "__socket" : {
      "name" : "__socket",
      "key" : "__socket",
      "type" : "java.net.Socket",
      "position" : {
        "startLine" : 38,
        "startColumn" : 20,
        "endLine" : 38,
        "endColumn" : 28
      },
      "modifiers" : [ "PRIVATE" ],
      "ignore" : false,
      "memberFieldKey" : "org.apache.commons.net.io.SocketOutputStream/memberField/__socket",
      "classOrInterfaceKey" : "org.apache.commons.net.io.SocketOutputStream"
    }
  },
  "methods" : {
    "write" : {
      "name" : "write",
      "key" : "org.apache.commons.net.io.SocketOutputStream/method/write",
      "type" : "void",
      "position" : {
        "startLine" : 67,
        "startColumn" : 17,
        "endLine" : 67,
        "endColumn" : 22
      },
      "modifiers" : [ "PUBLIC" ],
      "overrideAnnotation" : true,
      "returnType" : null,
      "parameters" : [ {
        "name" : "buffer",
        "key" : "buffer",
        "type" : "byte[]",
        "position" : {
          "startLine" : 67,
          "startColumn" : 28,
          "endLine" : 67,
          "endColumn" : 36
        },
        "modifiers" : [ ],
        "ignore" : false,
        "methodKey" : "org.apache.commons.net.io.SocketOutputStream/method/write"
      }, {
        "name" : "offset",
        "key" : "offset",
        "type" : "int",
        "position" : {
          "startLine" : 67,
          "startColumn" : 42,
          "endLine" : 67,
          "endColumn" : 48
        },
        "modifiers" : [ ],
        "ignore" : false,
        "methodKey" : "org.apache.commons.net.io.SocketOutputStream/method/write"
      }, {
        "name" : "length",
        "key" : "length",
        "type" : "int",
        "position" : {
          "startLine" : 67,
          "startColumn" : 54,
          "endLine" : 67,
          "endColumn" : 60
        },
        "modifiers" : [ ],
        "ignore" : false,
        "methodKey" : "org.apache.commons.net.io.SocketOutputStream/method/write"
      } ],
      "classOrInterfaceKey" : "org.apache.commons.net.io.SocketOutputStream"
    },
    "close" : {
      "name" : "close",
      "key" : "org.apache.commons.net.io.SocketOutputStream/method/close",
      "type" : "void",
      "position" : {
        "startLine" : 80,
        "startColumn" : 17,
        "endLine" : 80,
        "endColumn" : 22
      },
      "modifiers" : [ "PUBLIC" ],
      "overrideAnnotation" : true,
      "returnType" : null,
      "parameters" : [ ],
      "classOrInterfaceKey" : "org.apache.commons.net.io.SocketOutputStream"
    }
  },
  "fileKey" : null,
  "anonymous" : false,
  "auxclass" : false,
  "implements_" : [ ],
  "extends_" : [ "java.io.FilterOutputStream" ],
  "definedInClassOrInterfaceTypeKey" : null,
  "innerDefinedClasses" : { },
  "innerDefinedInterfaces" : { }
},
